barva/__init__.py
barva/__main__.py
barva/cli.py
barva/sampling.py
barva/source.py
barva/visualizer.py
barva/sources/__init__.py
barva/sources/native.py
barva/sources/pulseaudio.py
barva/utils/__init__.py
barva/utils/color.py
barva/utils/term.py
barva/visualizers/__init__.py
barva/visualizers/bars.py
barva/visualizers/pulse.py
barva-0.7.0.dist-info/LICENSE
barva-0.7.0.dist-info/METADATA
barva-0.7.0.dist-info/WHEEL
barva-0.7.0.dist-info/entry_points.txt
barva-0.7.0.dist-info/top_level.txt
barva-0.7.0.dist-info/RECORD
