Metadata-Version: 2.1
Name: barva
Version: 0.7.0
Summary: UNKNOWN
Home-page: https://github.com/Kharacternyk/barva
Author: UNKNOWN
Author-email: UNKNOWN
License: GPLv3+
Platform: UNKNOWN
Requires-Dist: numpy
